{
  "document_metadata": {
    "page_number": "1251",
    "document_number": "DOJ-OGR-00025445",
    "date": "2019/08/12",
    "document_type": "email",
    "has_handwriting": false,
    "has_stamps": false
  },
  "full_text": "Page 1251\nFwd: Re: Need you to reconstruct 292 data for Inmate Epstein, 76318-054\nFrom: Sonya Thompson\nTo: Michael Carvajal, Ray Ormond\nDate: 2019/08/12 12:43\nSubject: Fwd: Re: Need you to reconstruct 292 data for Inmate Epstein, 76318-054\nAttachments: TEXT.htm, Fwd: Re: Need you to reconstruct 292 data for Inmate Epstein, 76318-054\nSee attached. Staff working on retrieving the SRO data.\n\"Sent from a geospatial location known only by Skynet . . . err, Google\" â˜\n------- Original message -------\nFrom: (b)(6); (b)(7)(C) @bop.gov>\nDate: 8/12/19 12:20 PM (GMT-05:00)\nTo: (b)(6); (b)(7)(C) @bop.gov>, Sonya Thompson (b)(6); (b)(7)(C) @bop.gov>\nSubject: Fwd: Re: Need you to reconstruct 292 data for Inmate Epstein, 76318-054\nPage 3608\nDOJ-OGR-00025445",
  "text_blocks": [
    {
      "type": "printed",
      "content": "Fwd: Re: Need you to reconstruct 292 data for Inmate Epstein, 76318-054",
      "position": "header"
    },
    {
      "type": "printed",
      "content": "From: Sonya Thompson\nTo: Michael Carvajal, Ray Ormond\nDate: 2019/08/12 12:43\nSubject: Fwd: Re: Need you to reconstruct 292 data for Inmate Epstein, 76318-054\nAttachments: TEXT.htm, Fwd: Re: Need you to reconstruct 292 data for Inmate Epstein, 76318-054",
      "position": "header"
    },
    {
      "type": "printed",
      "content": "See attached. Staff working on retrieving the SRO data.",
      "position": "body"
    },
    {
      "type": "printed",
      "content": "\"Sent from a geospatial location known only by Skynet . . . err, Google\"",
      "position": "body"
    },
    {
      "type": "printed",
      "content": "------- Original message -------\nFrom: (b)(6); (b)(7)(C) @bop.gov>\nDate: 8/12/19 12:20 PM (GMT-05:00)\nTo: (b)(6); (b)(7)(C) @bop.gov>, Sonya Thompson (b)(6); (b)(7)(C) @bop.gov>\nSubject: Fwd: Re: Need you to reconstruct 292 data for Inmate Epstein, 76318-054",
      "position": "body"
    }
  ],
  "entities": {
    "people": [
      "Sonya Thompson",
      "Michael Carvajal",
      "Ray Ormond",
      "Epstein"
    ],
    "organizations": [
      "BOP"
    ],
    "locations": [],
    "dates": [
      "2019/08/12",
      "8/12/19"
    ],
    "reference_numbers": [
      "76318-054",
      "DOJ-OGR-00025445"
    ]
  },
  "additional_notes": "The document appears to be a forwarded email chain discussing the reconstruction of data for Inmate Epstein. Some email addresses and names are redacted."
}