{
  "document_metadata": {
    "page_number": "48",
    "document_number": "741",
    "date": "08/10/22",
    "document_type": "court document",
    "has_handwriting": false,
    "has_stamps": false
  },
  "full_text": "Case 1:20-cr-00330-PAE Document 741 Filed 08/10/22 Page 48 of 106 52 LBTCMAX2 Opening - Ms. Sternheim 1 radiated what's called a halo effect. He attracted people 2 because of his charisma and his charm, but he also 3 compartmentalized what he would disclose to people about his 4 life. 5 Now, you heard that he had a relationship with 6 Ghislaine, they became friends, became companions, but she 7 became his employee. She had the task, a time-consuming task 8 of developing and administering his real estate portfolio, the 9 multiple properties that each operated like small boutique 10 hotels. They were luxurious, they were vacation spots, and 11 like many New Yorkers, Epstein wintered and spent weekends in 12 Palm Beach. But unlike many New Yorkers, he did not summer in 13 the Hamptons he went to his ranch in Santa Fe, and he also went 14 to his home in the Virgin Islands. 15 You heard about his house having staff and house 16 managers because the houses required cleaning and maintenance, 17 housekeeping, gardening, all kinds of upkeep, purchase of 18 supplies, purchases of foods and sundries and meal preparation. 19 You will hear that Ghislaine visited those properties 20 with and without Epstein, and you will hear that Epstein spent 21 time with other women and traveled without Ghislaine. 22 (Continued on next page) 23 24 25 SOUTHERN DISTRICT REPORTERS, P.C. (212) 805-0300 DOJ-OGR-00011713",
  "text_blocks": [
    {
      "type": "printed",
      "content": "Case 1:20-cr-00330-PAE Document 741 Filed 08/10/22 Page 48 of 106 52 LBTCMAX2 Opening - Ms. Sternheim",
      "position": "header"
    },
    {
      "type": "printed",
      "content": "1 radiated what's called a halo effect. He attracted people 2 because of his charisma and his charm, but he also 3 compartmentalized what he would disclose to people about his 4 life. 5 Now, you heard that he had a relationship with 6 Ghislaine, they became friends, became companions, but she 7 became his employee. She had the task, a time-consuming task 8 of developing and administering his real estate portfolio, the 9 multiple properties that each operated like small boutique 10 hotels. They were luxurious, they were vacation spots, and 11 like many New Yorkers, Epstein wintered and spent weekends in 12 Palm Beach. But unlike many New Yorkers, he did not summer in 13 the Hamptons he went to his ranch in Santa Fe, and he also went 14 to his home in the Virgin Islands. 15 You heard about his house having staff and house 16 managers because the houses required cleaning and maintenance, 17 housekeeping, gardening, all kinds of upkeep, purchase of 18 supplies, purchases of foods and sundries and meal preparation. 19 You will hear that Ghislaine visited those properties 20 with and without Epstein, and you will hear that Epstein spent 21 time with other women and traveled without Ghislaine. 22 (Continued on next page) 23 24 25",
      "position": "main"
    },
    {
      "type": "printed",
      "content": "SOUTHERN DISTRICT REPORTERS, P.C. (212) 805-0300",
      "position": "footer"
    },
    {
      "type": "printed",
      "content": "DOJ-OGR-00011713",
      "position": "footer"
    }
  ],
  "entities": {
    "people": [
      "Epstein",
      "Ghislaine",
      "Ms. Sternheim"
    ],
    "organizations": [
      "SOUTHERN DISTRICT REPORTERS, P.C."
    ],
    "locations": [
      "New York",
      "Palm Beach",
      "Hamptons",
      "Santa Fe",
      "Virgin Islands"
    ],
    "dates": [
      "08/10/22"
    ],
    "reference_numbers": [
      "1:20-cr-00330-PAE",
      "741",
      "DOJ-OGR-00011713"
    ]
  },
  "additional_notes": "The document appears to be a court transcript. The text is clear and legible. There are no visible redactions or damage."
}