{
  "document_metadata": {
    "page_number": "25",
    "document_number": "109-1",
    "date": "09/17/2024",
    "document_type": "court document",
    "has_handwriting": false,
    "has_stamps": false
  },
  "full_text": "Case 22-1426, Document 109-1, 09/17/2024, 3634097, Page25 of 26\n\nwhere much of the abuse occurred and where Kellen worked.56 We therefore hold that the District Court did not err in applying the leadership enhancement.\n\nWith respect to the length of the sentence, the District Court properly discussed the sentencing factors when imposing the sentence, and described, at length, Maxwell's \"pivotal role in facilitating the abuse of the underaged girls through a series of deceptive tactics.\"57 The District Court recognized that the sentence \"must reflect the gravity of Ms. Maxwell's conduct, of Ms. Maxwell's offense, the pivotal role she played in facilitating the offense, and the significant and lasting harm it inflicted.\"58 And the District Court explained that \"a very serious, a very significant sentence is necessary to achieve the purposes of punishment\" under 18 U.S.C. ยง 3553(a). In sum, the District Court did not err by failing to adequately explain its sentence.\n\nCONCLUSION\n\nTo summarize, we hold as follows:\n\n56 A-417.\n57 SA-459.\n58 SA-461.\n\n25\nDOJ-OGR-00021819",
  "text_blocks": [
    {
      "type": "printed",
      "content": "Case 22-1426, Document 109-1, 09/17/2024, 3634097, Page25 of 26",
      "position": "header"
    },
    {
      "type": "printed",
      "content": "where much of the abuse occurred and where Kellen worked.56 We therefore hold that the District Court did not err in applying the leadership enhancement.",
      "position": "top"
    },
    {
      "type": "printed",
      "content": "With respect to the length of the sentence, the District Court properly discussed the sentencing factors when imposing the sentence, and described, at length, Maxwell's \"pivotal role in facilitating the abuse of the underaged girls through a series of deceptive tactics.\"57 The District Court recognized that the sentence \"must reflect the gravity of Ms. Maxwell's conduct, of Ms. Maxwell's offense, the pivotal role she played in facilitating the offense, and the significant and lasting harm it inflicted.\"58 And the District Court explained that \"a very serious, a very significant sentence is necessary to achieve the purposes of punishment\" under 18 U.S.C. ยง 3553(a). In sum, the District Court did not err by failing to adequately explain its sentence.",
      "position": "middle"
    },
    {
      "type": "printed",
      "content": "CONCLUSION",
      "position": "middle"
    },
    {
      "type": "printed",
      "content": "To summarize, we hold as follows:",
      "position": "middle"
    },
    {
      "type": "printed",
      "content": "56 A-417.\n57 SA-459.\n58 SA-461.",
      "position": "bottom"
    },
    {
      "type": "printed",
      "content": "25",
      "position": "footer"
    },
    {
      "type": "printed",
      "content": "DOJ-OGR-00021819",
      "position": "footer"
    }
  ],
  "entities": {
    "people": [
      "Kellen",
      "Maxwell"
    ],
    "organizations": [
      "District Court"
    ],
    "locations": [],
    "dates": [
      "09/17/2024"
    ],
    "reference_numbers": [
      "22-1426",
      "109-1",
      "3634097",
      "A-417",
      "SA-459",
      "SA-461",
      "DOJ-OGR-00021819"
    ]
  },
  "additional_notes": "The document appears to be a court document, specifically a page from a legal brief or opinion. The text is well-formatted and printed, with no visible handwriting or stamps. The content discusses a court case involving Maxwell and the application of sentencing factors."
}