{
  "document_metadata": {
    "page_number": "88",
    "document_number": "761",
    "date": "08/10/22",
    "document_type": "court transcript",
    "has_handwriting": false,
    "has_stamps": false
  },
  "full_text": "Case 1:20-cr-00330-PAE Document 761 Filed 08/10/22 Page 88 of 246 2383 LCGVMAX3 Espinosa - direct 1 A. Yes. 2 Q. And did you sit down for an interview with those 3 prosecutors in the case? 4 A. Yes. 5 Q. Do you recall when that was? 6 A. I think it was during the summer of this year. 7 Q. Do you remember the first time you sat down with them? Or 8 this may have been a videoconference? 9 A. It was a videoconference. 10 Q. Do you remember when that videoconference occurred? 11 A. No. 12 Q. I want to show you something that may refresh your 13 recollection. Do you see the folder that's below you on the 14 floor next to the chair? 15 MR. EVERDELL: With the Court's permission, I'll have 16 her turn to 3501.063-002, which should be behind tab 2 of your 17 materials. 18 THE COURT: Ms. Pomerantz, are you there? 19 MS. POMERANTZ: Yes, your Honor. 20 THE COURT: Okay. Go ahead. 21 Q. Do you have that document in front of you? 22 A. Yes. 23 Q. And if you could just look down at the bottom of the page 24 where there is some information on the left-hand side. Does 25 that refresh your recollection of when you had the SOUTHERN DISTRICT REPORTERS, P.C. (212) 805-0300 DOJ-OGR-00013947",
  "text_blocks": [
    {
      "type": "printed",
      "content": "Case 1:20-cr-00330-PAE Document 761 Filed 08/10/22 Page 88 of 246 2383 LCGVMAX3 Espinosa - direct",
      "position": "header"
    },
    {
      "type": "printed",
      "content": "1 A. Yes. 2 Q. And did you sit down for an interview with those 3 prosecutors in the case? 4 A. Yes. 5 Q. Do you recall when that was? 6 A. I think it was during the summer of this year. 7 Q. Do you remember the first time you sat down with them? Or 8 this may have been a videoconference? 9 A. It was a videoconference. 10 Q. Do you remember when that videoconference occurred? 11 A. No. 12 Q. I want to show you something that may refresh your 13 recollection. Do you see the folder that's below you on the 14 floor next to the chair? 15 MR. EVERDELL: With the Court's permission, I'll have 16 her turn to 3501.063-002, which should be behind tab 2 of your 17 materials. 18 THE COURT: Ms. Pomerantz, are you there? 19 MS. POMERANTZ: Yes, your Honor. 20 THE COURT: Okay. Go ahead. 21 Q. Do you have that document in front of you? 22 A. Yes. 23 Q. And if you could just look down at the bottom of the page 24 where there is some information on the left-hand side. Does 25 that refresh your recollection of when you had the",
      "position": "main content"
    },
    {
      "type": "printed",
      "content": "SOUTHERN DISTRICT REPORTERS, P.C. (212) 805-0300 DOJ-OGR-00013947",
      "position": "footer"
    }
  ],
  "entities": {
    "people": [
      "Espinosa",
      "MR. EVERDELL",
      "MS. POMERANTZ"
    ],
    "organizations": [
      "SOUTHERN DISTRICT REPORTERS, P.C."
    ],
    "locations": [],
    "dates": [
      "08/10/22"
    ],
    "reference_numbers": [
      "1:20-cr-00330-PAE",
      "761",
      "3501.063-002",
      "DOJ-OGR-00013947"
    ]
  },
  "additional_notes": "The document appears to be a court transcript with a clear and legible format. There are no visible redactions or damage."
}