{
  "document_metadata": {
    "page_number": "105",
    "document_number": "745",
    "date": "08/10/22",
    "document_type": "court transcript",
    "has_handwriting": false,
    "has_stamps": false
  },
  "full_text": "Case 1:20-cr-00330-PAE Document 745 Filed 08/10/22 Page 105 of 264 516 LC1VMAX3 Jane - cross 1 MS. MENNINGER: Okay. 2 Q. Isn't it true you told the government you do not remember 3 any specific abuse that occurred in New Mexico on the trips 4 that you took there? 5 A. I don't recall. 6 Q. And yesterday you testified about an incident in New Mexico 7 that you now specifically remember two years later. 8 A. That's right. 9 Q. Today you remember it; in 2020 you did not. 10 A. I don't recall saying any of what's written here. 11 Q. I'm going to ask you about the homes that you testified you 12 visited for Epstein in the mid 1990s, okay, between the ages of 13 14 and 16. 14 You recall in Palm Beach that you went to a pool 15 house; correct? 16 A. That's correct. 17 Q. And you only went to one house for Epstein in Palm Beach 18 ever; correct? 19 A. Yes. 20 Q. You remember the whole house in Florida was light-colored 21 and beachy; correct? 22 A. I think so; correct. 23 Q. You remember a winding staircase with pictures on the wall; 24 correct? 25 A. Correct. SOUTHERN DISTRICT REPORTERS, P.C. (212) 805-0300 DOJ-OGR-00012125",
  "text_blocks": [
    {
      "type": "printed",
      "content": "Case 1:20-cr-00330-PAE Document 745 Filed 08/10/22 Page 105 of 264 516",
      "position": "header"
    },
    {
      "type": "handwritten",
      "content": "LC1VMAX3 Jane - cross",
      "position": "header"
    },
    {
      "type": "printed",
      "content": "1 MS. MENNINGER: Okay. 2 Q. Isn't it true you told the government you do not remember 3 any specific abuse that occurred in New Mexico on the trips 4 that you took there? 5 A. I don't recall. 6 Q. And yesterday you testified about an incident in New Mexico 7 that you now specifically remember two years later. 8 A. That's right. 9 Q. Today you remember it; in 2020 you did not. 10 A. I don't recall saying any of what's written here. 11 Q. I'm going to ask you about the homes that you testified you 12 visited for Epstein in the mid 1990s, okay, between the ages of 13 14 and 16. 14 You recall in Palm Beach that you went to a pool 15 house; correct? 16 A. That's correct. 17 Q. And you only went to one house for Epstein in Palm Beach 18 ever; correct? 19 A. Yes. 20 Q. You remember the whole house in Florida was light-colored 21 and beachy; correct? 22 A. I think so; correct. 23 Q. You remember a winding staircase with pictures on the wall; 24 correct? 25 A. Correct.",
      "position": "main"
    },
    {
      "type": "printed",
      "content": "SOUTHERN DISTRICT REPORTERS, P.C. (212) 805-0300",
      "position": "footer"
    },
    {
      "type": "printed",
      "content": "DOJ-OGR-00012125",
      "position": "footer"
    }
  ],
  "entities": {
    "people": [
      "MS. MENNINGER",
      "Epstein"
    ],
    "organizations": [
      "SOUTHERN DISTRICT REPORTERS, P.C."
    ],
    "locations": [
      "New Mexico",
      "Palm Beach",
      "Florida"
    ],
    "dates": [
      "08/10/22",
      "2020",
      "mid 1990s"
    ],
    "reference_numbers": [
      "1:20-cr-00330-PAE",
      "745",
      "DOJ-OGR-00012125"
    ]
  },
  "additional_notes": "The document appears to be a court transcript with a clear and legible format. There are no visible redactions or damage."
}